[
  {
    "title": "Exercise 1 - Buy",
    "date": "2026-04-20",
    "starting_capital": 1000.0,
    "cash_held": 50.0,
    "trades": [
      {
        "ticker": "NVDA",
        "action": "BUY",
        "time": "15:21",
        "entry": 198.81,
        "eod": 202.06,
        "allocated": 200.0,
        "units": 1.006,
        "pnl": 3.27,
        "pnl_pct": 1.63,
        "rating": "MAYBE",
        "vol_ratio": 0.9
      },
      {
        "ticker": "META",
        "action": "BUY",
        "time": "13:58",
        "entry": 678.06,
        "eod": 670.91,
        "allocated": 350.0,
        "units": 0.5162,
        "pnl": -3.69,
        "pnl_pct": -1.05,
        "rating": "TAKE",
        "vol_ratio": 1.3
      },
      {
        "ticker": "PLTR",
        "action": "BUY",
        "time": "15:21",
        "entry": 144.82,
        "eod": 145.89,
        "allocated": 200.0,
        "units": 1.381,
        "pnl": 1.48,
        "pnl_pct": 0.74,
        "rating": "MAYBE",
        "vol_ratio": 1.0
      },
      {
        "ticker": "MSTR",
        "action": "BUY",
        "time": "14:20",
        "entry": 165.46,
        "eod": 170.81,
        "allocated": 200.0,
        "units": 1.2088,
        "pnl": 6.47,
        "pnl_pct": 3.23,
        "rating": "MAYBE",
        "vol_ratio": 0.8
      }
    ],
    "total_invested": 950.0,
    "eod_value": 957.53,
    "total_pnl": 7.53,
    "total_pnl_pct": 0.79,
    "portfolio_eod": 1007.53
  }
]